pinjected_anthopic/__init__.py
pinjected_anthopic-0.1.1.dist-info/METADATA
pinjected_anthopic-0.1.1.dist-info/WHEEL
pinjected_anthopic-0.1.1.dist-info/RECORD
