Metadata-Version: 2.3
Name: pinjected-anthopic
Version: 0.1.1
Summary: Add your description here
Author-email: proboscis <nameissoap@gmail.com>
Requires-Python: >=3.8
Requires-Dist: anthropic>=0.34.1
Requires-Dist: pillow>=10.4.0
Requires-Dist: pinjected>=0.2.189
